odoo/addons/l10n_fr_account_invoice_facturx/README.rst
odoo/addons/l10n_fr_account_invoice_facturx/__init__.py
odoo/addons/l10n_fr_account_invoice_facturx/__manifest__.py
odoo/addons/l10n_fr_account_invoice_facturx/i18n/es.po
odoo/addons/l10n_fr_account_invoice_facturx/i18n/fr.po
odoo/addons/l10n_fr_account_invoice_facturx/i18n/l10n_fr_account_invoice_factur-x.pot
odoo/addons/l10n_fr_account_invoice_facturx/i18n/l10n_fr_account_invoice_facturx.pot
odoo/addons/l10n_fr_account_invoice_facturx/models/__init__.py
odoo/addons/l10n_fr_account_invoice_facturx/models/account_move.py
odoo/addons/l10n_fr_account_invoice_facturx/readme/CONTRIBUTORS.md
odoo/addons/l10n_fr_account_invoice_facturx/readme/DESCRIPTION.md
odoo/addons/l10n_fr_account_invoice_facturx/static/description/icon.png
odoo/addons/l10n_fr_account_invoice_facturx/static/description/index.html
odoo_addon_l10n_fr_account_invoice_facturx-18.0.1.0.0.2.dist-info/METADATA
odoo_addon_l10n_fr_account_invoice_facturx-18.0.1.0.0.2.dist-info/WHEEL
odoo_addon_l10n_fr_account_invoice_facturx-18.0.1.0.0.2.dist-info/top_level.txt
odoo_addon_l10n_fr_account_invoice_facturx-18.0.1.0.0.2.dist-info/RECORD
